<?xml version="1.0" encoding="UTF-8"?>
<MF0 version="1.1" packageUris="http://schema.mathworks.com/mf0/sl_modelref_info/R2020a http://schema.mathworks.com/mf0/slexec_mm_sto/R2019b_201902271317">
  <ModelRefInfoRepo.ModelRefInfoRoot type="ModelRefInfoRepo.ModelRefInfoRoot" uuid="82078ac9-abc3-41c9-a26f-6d3c0c8cc5d9">
    <autoSolverStatusFlags>323</autoSolverStatusFlags>
    <childModelRefInfo type="ModelRefInfoRepo.ChildModelRefInfo" uuid="8c8891e6-cf2a-44b7-8734-86a95a384b33">
      <modelName>EvPowertrainController</modelName>
      <modelPath>EvPowertrainController</modelPath>
    </childModelRefInfo>
    <compDerivCacheNeedsReset>false</compDerivCacheNeedsReset>
    <compZcCacheNeedsReset>false</compZcCacheNeedsReset>
    <dataTransferInfos>AAFJTQAAAAAOAAAAOAAAAAYAAAAIAAAAAgAAAAAAAAAFAAAACAAAAAAAAAABAAAAAQAAAAAAAAAFAAQAAQAAAAEAAAAAAAAA</dataTransferInfos>
    <defaultsCMapping>{&quot;Inports&quot;:&quot;{\&quot;Name\&quot;:\&quot;Default\&quot;,\&quot;Checksum\&quot;:\&quot;Default\&quot;,\&quot;PerInstancePropertiesChecksum\&quot;:\&quot;\&quot;,\&quot;MemorySectionName\&quot;:\&quot;None\&quot;,\&quot;MemorySectionChecksum\&quot;:\&quot;None\&quot;}&quot;,&quot;Outports&quot;:&quot;{\&quot;Name\&quot;:\&quot;Default\&quot;,\&quot;Checksum\&quot;:\&quot;Default\&quot;,\&quot;PerInstancePropertiesChecksum\&quot;:\&quot;\&quot;,\&quot;MemorySectionName\&quot;:\&quot;None\&quot;,\&quot;MemorySectionChecksum\&quot;:\&quot;None\&quot;}&quot;,&quot;LocalParameters&quot;:&quot;{\&quot;Name\&quot;:\&quot;Default\&quot;,\&quot;Checksum\&quot;:\&quot;Default\&quot;,\&quot;PerInstancePropertiesChecksum\&quot;:\&quot;\&quot;,\&quot;MemorySectionName\&quot;:\&quot;None\&quot;,\&quot;MemorySectionChecksum\&quot;:\&quot;None\&quot;}&quot;,&quot;ParameterArguments&quot;:&quot;{\&quot;Name\&quot;:\&quot;Default\&quot;,\&quot;Checksum\&quot;:\&quot;Default\&quot;,\&quot;PerInstancePropertiesChecksum\&quot;:\&quot;\&quot;,\&quot;MemorySectionName\&quot;:\&quot;None\&quot;,\&quot;MemorySectionChecksum\&quot;:\&quot;None\&quot;}&quot;,&quot;GlobalParameters&quot;:&quot;{\&quot;Name\&quot;:\&quot;Default\&quot;,\&quot;Checksum\&quot;:\&quot;Default\&quot;,\&quot;PerInstancePropertiesChecksum\&quot;:\&quot;\&quot;,\&quot;MemorySectionName\&quot;:\&quot;None\&quot;,\&quot;MemorySectionChecksum\&quot;:\&quot;None\&quot;}&quot;,&quot;SharedLocalDataStores&quot;:&quot;{\&quot;Name\&quot;:\&quot;Default\&quot;,\&quot;Checksum\&quot;:\&quot;Default\&quot;,\&quot;PerInstancePropertiesChecksum\&quot;:\&quot;\&quot;,\&quot;MemorySectionName\&quot;:\&quot;None\&quot;,\&quot;MemorySectionChecksum\&quot;:\&quot;None\&quot;}&quot;,&quot;GlobalDataStores&quot;:&quot;{\&quot;Name\&quot;:\&quot;Default\&quot;,\&quot;Checksum\&quot;:\&quot;Default\&quot;,\&quot;PerInstancePropertiesChecksum\&quot;:\&quot;\&quot;,\&quot;MemorySectionName\&quot;:\&quot;None\&quot;,\&quot;MemorySectionChecksum\&quot;:\&quot;None\&quot;}&quot;,&quot;InternalData&quot;:&quot;{\&quot;Name\&quot;:\&quot;Default\&quot;,\&quot;Checksum\&quot;:\&quot;Default\&quot;,\&quot;PerInstancePropertiesChecksum\&quot;:\&quot;\&quot;,\&quot;MemorySectionName\&quot;:\&quot;None\&quot;,\&quot;MemorySectionChecksum\&quot;:\&quot;None\&quot;}&quot;,&quot;Constants&quot;:&quot;{\&quot;Name\&quot;:\&quot;Default\&quot;,\&quot;Checksum\&quot;:\&quot;Default\&quot;,\&quot;PerInstancePropertiesChecksum\&quot;:\&quot;\&quot;,\&quot;MemorySectionName\&quot;:\&quot;None\&quot;,\&quot;MemorySectionChecksum\&quot;:\&quot;None\&quot;}&quot;,&quot;DataTransfers&quot;:&quot;{\&quot;Name\&quot;:\&quot;Default\&quot;,\&quot;Checksum\&quot;:\&quot;Default\&quot;,\&quot;PerInstancePropertiesChecksum\&quot;:\&quot;\&quot;,\&quot;MemorySectionName\&quot;:\&quot;None\&quot;,\&quot;MemorySectionChecksum\&quot;:\&quot;None\&quot;}&quot;,&quot;ModelData&quot;:&quot;{\&quot;Name\&quot;:\&quot;Default\&quot;,\&quot;Checksum\&quot;:\&quot;Default\&quot;,\&quot;PerInstancePropertiesChecksum\&quot;:\&quot;\&quot;,\&quot;MemorySectionName\&quot;:\&quot;None\&quot;,\&quot;MemorySectionChecksum\&quot;:\&quot;None\&quot;}&quot;,&quot;InitializeTerminate&quot;:&quot;{\&quot;Name\&quot;:\&quot;Default\&quot;,\&quot;Checksum\&quot;:\&quot;Default\&quot;,\&quot;PerInstancePropertiesChecksum\&quot;:\&quot;\&quot;,\&quot;MemorySectionName\&quot;:\&quot;None\&quot;,\&quot;MemorySectionChecksum\&quot;:\&quot;None\&quot;}&quot;,&quot;Execution&quot;:&quot;{\&quot;Name\&quot;:\&quot;Default\&quot;,\&quot;Checksum\&quot;:\&quot;Default\&quot;,\&quot;PerInstancePropertiesChecksum\&quot;:\&quot;\&quot;,\&quot;MemorySectionName\&quot;:\&quot;None\&quot;,\&quot;MemorySectionChecksum\&quot;:\&quot;None\&quot;}&quot;,&quot;SharedUtility&quot;:&quot;{\&quot;Name\&quot;:\&quot;Default\&quot;,\&quot;Checksum\&quot;:\&quot;Default\&quot;,\&quot;PerInstancePropertiesChecksum\&quot;:\&quot;\&quot;,\&quot;MemorySectionName\&quot;:\&quot;None\&quot;,\&quot;MemorySectionChecksum\&quot;:\&quot;None\&quot;}&quot;}</defaultsCMapping>
    <fundamentalSampleTimePeriod>0.01</fundamentalSampleTimePeriod>
    <hasBlockWithPeriodicDiscreteSampleTime>true</hasBlockWithPeriodicDiscreteSampleTime>
    <hasBwsAccessed>true</hasBwsAccessed>
    <hasBwsAccessedByAnyModel>true</hasBwsAccessedByAnyModel>
    <hasConstantOutput>false</hasConstantOutput>
    <hasInternalModelWideEventTs>true</hasInternalModelWideEventTs>
    <hasModelWideEventTs>true</hasModelWideEventTs>
    <hasNonVirtualConstantTs>true</hasNonVirtualConstantTs>
    <hasNonVirtualParameterChangeEvents>true</hasNonVirtualParameterChangeEvents>
    <hasVariantModelOrSubsystem>true</hasVariantModelOrSubsystem>
    <inports type="ModelRefInfoRepo.InportInformation" uuid="92ef3594-6803-47ed-9efc-a6f872e034dd">
      <isNotDerivPort>true</isNotDerivPort>
      <designMax>inf</designMax>
      <designMin>-inf</designMin>
      <indexType>2</indexType>
      <rateInfo type="ModelRefInfoRepo.RateInfo">
        <compiled>true</compiled>
        <nonFcnCallPartitionName>D1</nonFcnCallPartitionName>
        <period>0.01</period>
        <priority>40</priority>
        <rateIdx>0</rateIdx>
      </rateInfo>
      <resolvedSignalObject></resolvedSignalObject>
      <sigNameToEMVCEMap type="ModelRefInfoRepo.SigNameEMVCEInfo" uuid="67740806-b3dc-4e54-964d-41202adbf779"/>
    </inports>
    <inports type="ModelRefInfoRepo.InportInformation" uuid="4e4b28e8-f3fc-4c9a-a5b8-4947da1a8871">
      <isNotDerivPort>true</isNotDerivPort>
      <designMax>inf</designMax>
      <designMin>-inf</designMin>
      <indexType>2</indexType>
      <originalPortNumber>1</originalPortNumber>
      <rateInfo type="ModelRefInfoRepo.RateInfo">
        <compiled>true</compiled>
        <nonFcnCallPartitionName>D1</nonFcnCallPartitionName>
        <period>0.01</period>
        <priority>40</priority>
        <rateIdx>0</rateIdx>
      </rateInfo>
      <resolvedSignalObject></resolvedSignalObject>
      <sigNameToEMVCEMap type="ModelRefInfoRepo.SigNameEMVCEInfo" uuid="3802714c-a602-46f3-a802-518166e6d0e1"/>
    </inports>
    <inports type="ModelRefInfoRepo.InportInformation" uuid="3d70afcc-024b-4ea7-9275-e44fbd0b6e5d">
      <isNotDerivPort>true</isNotDerivPort>
      <designMax>inf</designMax>
      <designMin>-inf</designMin>
      <indexType>2</indexType>
      <originalPortNumber>2</originalPortNumber>
      <rateInfo type="ModelRefInfoRepo.RateInfo">
        <compiled>true</compiled>
        <nonFcnCallPartitionName>D1</nonFcnCallPartitionName>
        <period>0.01</period>
        <priority>40</priority>
        <rateIdx>0</rateIdx>
      </rateInfo>
      <resolvedSignalObject></resolvedSignalObject>
      <sigNameToEMVCEMap type="ModelRefInfoRepo.SigNameEMVCEInfo" uuid="021dc51c-07ed-45fa-8625-fcc161fc1f9b"/>
    </inports>
    <inports type="ModelRefInfoRepo.InportInformation" uuid="c17257d6-0b63-47db-a65b-876c59b032ed">
      <isNotDerivPort>true</isNotDerivPort>
      <designMax>inf</designMax>
      <designMin>-inf</designMin>
      <indexType>2</indexType>
      <originalPortNumber>3</originalPortNumber>
      <rateInfo type="ModelRefInfoRepo.RateInfo">
        <compiled>true</compiled>
        <nonFcnCallPartitionName>D1</nonFcnCallPartitionName>
        <period>0.01</period>
        <priority>40</priority>
        <rateIdx>0</rateIdx>
      </rateInfo>
      <resolvedSignalObject></resolvedSignalObject>
      <sigNameToEMVCEMap type="ModelRefInfoRepo.SigNameEMVCEInfo" uuid="68ef5ee4-8d67-4188-9d87-83276788ec7d"/>
    </inports>
    <inports type="ModelRefInfoRepo.InportInformation" uuid="1ccecdd2-1d91-4e24-bc66-72a61799e36a">
      <isNotDerivPort>true</isNotDerivPort>
      <designMax>inf</designMax>
      <designMin>-inf</designMin>
      <indexType>2</indexType>
      <originalPortNumber>4</originalPortNumber>
      <rateInfo type="ModelRefInfoRepo.RateInfo">
        <compiled>true</compiled>
        <nonFcnCallPartitionName>D1</nonFcnCallPartitionName>
        <period>0.01</period>
        <priority>40</priority>
        <rateIdx>0</rateIdx>
      </rateInfo>
      <resolvedSignalObject></resolvedSignalObject>
      <sigNameToEMVCEMap type="ModelRefInfoRepo.SigNameEMVCEInfo" uuid="aeb84c1d-a4fa-498f-8d9c-29a33cfcf5fc"/>
    </inports>
    <inports type="ModelRefInfoRepo.InportInformation" uuid="41e40f6c-b770-403f-99a7-5176d71cc9dc">
      <isNotDerivPort>true</isNotDerivPort>
      <designMax>inf</designMax>
      <designMin>-inf</designMin>
      <indexType>2</indexType>
      <originalPortNumber>5</originalPortNumber>
      <rateInfo type="ModelRefInfoRepo.RateInfo">
        <compiled>true</compiled>
        <nonFcnCallPartitionName>D1</nonFcnCallPartitionName>
        <period>0.01</period>
        <priority>40</priority>
        <rateIdx>0</rateIdx>
      </rateInfo>
      <resolvedSignalObject></resolvedSignalObject>
      <sigNameToEMVCEMap type="ModelRefInfoRepo.SigNameEMVCEInfo" uuid="63ad7b65-51c5-4b38-b873-fe264e43bff5"/>
    </inports>
    <inports type="ModelRefInfoRepo.InportInformation" uuid="bdc1699f-c4e0-4715-af58-594f0126c57d">
      <isNotDerivPort>true</isNotDerivPort>
      <designMax>inf</designMax>
      <designMin>-inf</designMin>
      <indexType>2</indexType>
      <originalPortNumber>6</originalPortNumber>
      <rateInfo type="ModelRefInfoRepo.RateInfo">
        <compiled>true</compiled>
        <nonFcnCallPartitionName>D1</nonFcnCallPartitionName>
        <period>0.01</period>
        <priority>40</priority>
        <rateIdx>0</rateIdx>
      </rateInfo>
      <resolvedSignalObject></resolvedSignalObject>
      <sigNameToEMVCEMap type="ModelRefInfoRepo.SigNameEMVCEInfo" uuid="1125cfe5-8723-4b5a-9f8c-42dd69688c6e"/>
    </inports>
    <isAperiodicRootFcnCallSystem>false</isAperiodicRootFcnCallSystem>
    <isOrigInportVirtualBus>false</isOrigInportVirtualBus>
    <isOrigInportVirtualBus>false</isOrigInportVirtualBus>
    <isOrigInportVirtualBus>false</isOrigInportVirtualBus>
    <isOrigInportVirtualBus>false</isOrigInportVirtualBus>
    <isOrigInportVirtualBus>false</isOrigInportVirtualBus>
    <isOrigInportVirtualBus>false</isOrigInportVirtualBus>
    <isOrigInportVirtualBus>false</isOrigInportVirtualBus>
    <isOrigOutportVirtualBus>false</isOrigOutportVirtualBus>
    <isOrigOutportVirtualBus>false</isOrigOutportVirtualBus>
    <isPreCompSingleRate>false</isPreCompSingleRate>
    <isRefModelConstant>false</isRefModelConstant>
    <isRootFcnCallPortGroupsEmpty>true</isRootFcnCallPortGroupsEmpty>
    <loggingSaveFormat>2</loggingSaveFormat>
    <maxFreqHz>-1</maxFreqHz>
    <numModelWideEventTs>1</numModelWideEventTs>
    <numPortlessSimulinkFunctionPortGroups>0</numPortlessSimulinkFunctionPortGroups>
    <numRuntimeExportedRates>1</numRuntimeExportedRates>
    <numTs>2</numTs>
    <origInportBusType></origInportBusType>
    <origInportBusType></origInportBusType>
    <origInportBusType></origInportBusType>
    <origInportBusType></origInportBusType>
    <origInportBusType></origInportBusType>
    <origInportBusType></origInportBusType>
    <origInportBusType></origInportBusType>
    <origOutportBusOutputAsStruct>false</origOutportBusOutputAsStruct>
    <origOutportBusOutputAsStruct>false</origOutportBusOutputAsStruct>
    <origOutportBusType></origOutportBusType>
    <origOutportBusType></origOutportBusType>
    <outports type="ModelRefInfoRepo.OutportInformation" uuid="16bafa93-d6a7-4ded-a5d9-d1a308abf1af">
      <designMax>inf</designMax>
      <designMin>-inf</designMin>
      <indexType>2</indexType>
      <rateInfo type="ModelRefInfoRepo.RateInfo">
        <compiled>true</compiled>
        <nonFcnCallPartitionName>D1</nonFcnCallPartitionName>
        <period>0.01</period>
        <priority>40</priority>
        <rateIdx>0</rateIdx>
      </rateInfo>
      <resolvedSignalObject></resolvedSignalObject>
      <sigNameToEMVCEMap type="ModelRefInfoRepo.SigNameEMVCEInfo" uuid="00b53dc9-2c11-4257-b945-0747c887035d"/>
    </outports>
    <outports type="ModelRefInfoRepo.OutportInformation" uuid="d63dd0e4-8e22-4299-b1b8-6ce9d724b56d">
      <designMax>inf</designMax>
      <designMin>-inf</designMin>
      <indexType>2</indexType>
      <originalPortNumber>1</originalPortNumber>
      <rateInfo type="ModelRefInfoRepo.RateInfo">
        <compiled>true</compiled>
        <nonFcnCallPartitionName>D1</nonFcnCallPartitionName>
        <period>0.01</period>
        <priority>40</priority>
        <rateIdx>0</rateIdx>
      </rateInfo>
      <resolvedSignalObject></resolvedSignalObject>
      <sigNameToEMVCEMap type="ModelRefInfoRepo.SigNameEMVCEInfo" uuid="f48c61eb-963c-47ab-bc33-4a0f66535c4a"/>
    </outports>
    <preCompAllowConstTsOnPorts>false</preCompAllowConstTsOnPorts>
    <preCompAllowPortBasedInTriggeredSS>false</preCompAllowPortBasedInTriggeredSS>
    <runtimeNonFcnCallRateInfos type="ModelRefInfoRepo.RateInfo">
      <compiled>true</compiled>
      <nonFcnCallPartitionName>D1</nonFcnCallPartitionName>
      <period>0.01</period>
      <priority>40</priority>
      <rateIdx>0</rateIdx>
    </runtimeNonFcnCallRateInfos>
    <sampleTimeInheritanceRule>2</sampleTimeInheritanceRule>
    <timingAndTaskingRegistry>&lt;?xml version=&quot;1.0&quot;?&gt;
&lt;slexec_sto version=&quot;1.1&quot; packageUris=&quot;http://schema.mathworks.com/mf0/slexec_mm_sto/R2019b_201902271317&quot;&gt;
  &lt;sto.Registry type=&quot;sto.Registry&quot; uuid=&quot;8c355f05-f5ed-4c07-b154-0a9042114b49&quot;&gt;
    &lt;clocks type=&quot;sto.Timer&quot; uuid=&quot;6b1e848f-35e5-4671-ae72-cf34d0dd7a12&quot;&gt;
      &lt;needsToProvideTimeDuringExecution&gt;true&lt;/needsToProvideTimeDuringExecution&gt;
      &lt;clockTickConstraint&gt;PeriodicWithFixedResolution&lt;/clockTickConstraint&gt;
      &lt;resolution&gt;0.01&lt;/resolution&gt;
      &lt;specifiedTaskingMode&gt;ClassicMultiTasking&lt;/specifiedTaskingMode&gt;
      &lt;timeAdvanceMode&gt;FixedStep&lt;/timeAdvanceMode&gt;
      &lt;clockDomain type=&quot;sto.ClockDomain&quot; uuid=&quot;14be775d-f342-4d98-aa4c-ae0500115ca2&quot;&gt;
        &lt;baseTaskID&gt;_task0&lt;/baseTaskID&gt;
        &lt;computedFundamentalStepSize&gt;0.01&lt;/computedFundamentalStepSize&gt;
        &lt;rates type=&quot;sto.Rate&quot; uuid=&quot;da515fcf-fcf7-4a91-a82a-137e555e8923&quot;/&gt;
        &lt;rootTaskHierarchyElements type=&quot;sto.Task&quot; uuid=&quot;3628f602-e334-4d4b-9bf1-423e85aa17e1&quot;&gt;
          &lt;isExecutable&gt;true&lt;/isExecutable&gt;
          &lt;orderIndex&gt;1&lt;/orderIndex&gt;
          &lt;rates type=&quot;sto.Rate&quot; uuid=&quot;da515fcf-fcf7-4a91-a82a-137e555e8923&quot;&gt;
            &lt;annotation&gt;D1&lt;/annotation&gt;
            &lt;colorIndex&gt;2&lt;/colorIndex&gt;
            &lt;description&gt;Discrete 1&lt;/description&gt;
            &lt;eventSourceType&gt;UNSPECIFIED_EVENT_SOURCE&lt;/eventSourceType&gt;
            &lt;registry type=&quot;sto.Registry&quot; uuid=&quot;8c355f05-f5ed-4c07-b154-0a9042114b49&quot;/&gt;
            &lt;taskId&gt;_task0&lt;/taskId&gt;
            &lt;rateSpec type=&quot;sto.RateSpec&quot; uuid=&quot;bc8b9ccb-7356-45cd-8a71-e88437909260&quot;&gt;
              &lt;period&gt;0.01&lt;/period&gt;
              &lt;rateType&gt;ClassicPeriodicDiscrete&lt;/rateType&gt;
            &lt;/rateSpec&gt;
          &lt;/rates&gt;
          &lt;elementType&gt;Task&lt;/elementType&gt;
          &lt;identifier&gt;_task0&lt;/identifier&gt;
          &lt;priority&gt;40&lt;/priority&gt;
        &lt;/rootTaskHierarchyElements&gt;
      &lt;/clockDomain&gt;
    &lt;/clocks&gt;
    &lt;clocks type=&quot;sto.Event&quot; uuid=&quot;4247bf7b-cab5-462f-9792-8146818ba2e5&quot;&gt;
      &lt;eventType&gt;PARAMETER_CHANGE_EVENT&lt;/eventType&gt;
      &lt;cNum&gt;1&lt;/cNum&gt;
      &lt;clockType&gt;Event&lt;/clockType&gt;
      &lt;identifier&gt;ParameterChangeEvent&lt;/identifier&gt;
      &lt;resolution&gt;-1&lt;/resolution&gt;
      &lt;specifiedTaskingMode&gt;ExplicitTasking&lt;/specifiedTaskingMode&gt;
      &lt;timeAdvanceMode&gt;None&lt;/timeAdvanceMode&gt;
      &lt;clockDomain type=&quot;sto.ClockDomain&quot; uuid=&quot;0d8888e8-b057-40b8-b9af-e9854b663371&quot;&gt;
        &lt;computedFundamentalStepSize&gt;-1&lt;/computedFundamentalStepSize&gt;
        &lt;rates type=&quot;sto.Rate&quot; uuid=&quot;187587b4-0d81-4162-9cb4-42022898f706&quot;/&gt;
        &lt;rootTaskHierarchyElements type=&quot;sto.Task&quot; uuid=&quot;680a9794-98f1-4834-b7b8-c439d2776878&quot;&gt;
          &lt;isExecutable&gt;true&lt;/isExecutable&gt;
          &lt;isExplicit&gt;true&lt;/isExplicit&gt;
          &lt;rates type=&quot;sto.Rate&quot; uuid=&quot;187587b4-0d81-4162-9cb4-42022898f706&quot;&gt;
            &lt;annotation&gt;Inf&lt;/annotation&gt;
            &lt;colorIndex&gt;6&lt;/colorIndex&gt;
            &lt;description&gt;Constant&lt;/description&gt;
            &lt;eventSourceType&gt;PARAMETER_CHANGE_EVENT&lt;/eventSourceType&gt;
            &lt;rateIDX&gt;1&lt;/rateIDX&gt;
            &lt;registry type=&quot;sto.Registry&quot; uuid=&quot;8c355f05-f5ed-4c07-b154-0a9042114b49&quot;/&gt;
            &lt;stringID&gt;ParameterChangeEvent&lt;/stringID&gt;
            &lt;taskId&gt;ModelWideParameterChangeEvent&lt;/taskId&gt;
            &lt;rateSpec type=&quot;sto.RateSpec&quot; uuid=&quot;bde1cd1c-73ab-4bb9-8ac5-35420054b4e2&quot;&gt;
              &lt;period&gt;inf&lt;/period&gt;
              &lt;rateType&gt;ModelWideParameterChangeEvent&lt;/rateType&gt;
            &lt;/rateSpec&gt;
          &lt;/rates&gt;
          &lt;tNum&gt;1&lt;/tNum&gt;
          &lt;elementType&gt;Task&lt;/elementType&gt;
          &lt;identifier&gt;ModelWideParameterChangeEvent&lt;/identifier&gt;
          &lt;priority&gt;-1&lt;/priority&gt;
          &lt;schedulingClockID&gt;ParameterChangeEvent&lt;/schedulingClockID&gt;
        &lt;/rootTaskHierarchyElements&gt;
      &lt;/clockDomain&gt;
    &lt;/clocks&gt;
    &lt;executionSpec&gt;Undetermined&lt;/executionSpec&gt;
    &lt;hasUnknownEdges&gt;true&lt;/hasUnknownEdges&gt;
    &lt;taskDependencyGraph type=&quot;sto.SerializedTaskConnectionList&quot; uuid=&quot;9b53cbcd-af69-4370-914c-30fb94c61323&quot;&gt;
      &lt;taskIdentifier&gt;_task0&lt;/taskIdentifier&gt;
    &lt;/taskDependencyGraph&gt;
    &lt;taskDependencyGraph type=&quot;sto.SerializedTaskConnectionList&quot; uuid=&quot;957e0125-b0a6-4f42-9390-33fa1ffdc413&quot;&gt;
      &lt;clockIdentifier&gt;ParameterChangeEvent&lt;/clockIdentifier&gt;
      &lt;serializedConnectionProperties type=&quot;sto.SerializedConnectionProperties&quot; uuid=&quot;2df0f1bb-dca5-4d56-8a73-9bc72b01827a&quot;&gt;
        &lt;targetTaskIdentifier&gt;_task0&lt;/targetTaskIdentifier&gt;
      &lt;/serializedConnectionProperties&gt;
      &lt;taskIdentifier&gt;ModelWideParameterChangeEvent&lt;/taskIdentifier&gt;
    &lt;/taskDependencyGraph&gt;
    &lt;taskPriorityDirection&gt;HighNumberLast&lt;/taskPriorityDirection&gt;
    &lt;taskingMode&gt;ClassicMultiTasking&lt;/taskingMode&gt;
    &lt;tasks type=&quot;sto.Task&quot; uuid=&quot;3628f602-e334-4d4b-9bf1-423e85aa17e1&quot;/&gt;
    &lt;tasks type=&quot;sto.Task&quot; uuid=&quot;680a9794-98f1-4834-b7b8-c439d2776878&quot;/&gt;
    &lt;timeAdvanceMode&gt;FixedStep&lt;/timeAdvanceMode&gt;
  &lt;/sto.Registry&gt;
&lt;/slexec_sto&gt;</timingAndTaskingRegistry>
    <usePortBasedSampleTime>false</usePortBasedSampleTime>
    <userSpecifiedFixedStepSize>0.01</userSpecifiedFixedStepSize>
    <FMUBlockMap type="ModelRefInfoRepo.FMUBlockInfo" uuid="dceb83d2-c081-4797-88ce-9db01e5b50a6"/>
    <codeGenInfo type="ModelRefInfoRepo.CodeGenInformation" uuid="a72580b8-c3e3-4120-ad9b-8213f2e128f1">
      <DWorkTypeName>pwecol01r52</DWorkTypeName>
    </codeGenInfo>
    <configSettingsForConsistencyChecks type="ModelRefInfoRepo.ConfigSettingsForConsistencyChecks" uuid="5a34a981-4f4e-4cac-925d-fb577e28e4e5">
      <fixedStepSize>0.01</fixedStepSize>
      <frameDiagnosticSetting>2</frameDiagnosticSetting>
      <hasHybridSampleTime>true</hasHybridSampleTime>
      <signalLoggingSaveFormat>2</signalLoggingSaveFormat>
      <solverName>FixedStepDiscrete</solverName>
      <solverType>SOLVER_TYPE_FIXEDSTEP</solverType>
      <hardwareSettings type="ModelRefInfoRepo.HardwareSettings" uuid="d9bb0d77-18fd-4830-8ed3-62e6bc04be56">
        <prodBitPerChar>8</prodBitPerChar>
        <prodBitPerDouble>64</prodBitPerDouble>
        <prodBitPerFloat>32</prodBitPerFloat>
        <prodBitPerInt>32</prodBitPerInt>
        <prodBitPerLong>32</prodBitPerLong>
        <prodBitPerLongLong>64</prodBitPerLongLong>
        <prodBitPerPointer>64</prodBitPerPointer>
        <prodBitPerPtrDiffT>64</prodBitPerPtrDiffT>
        <prodBitPerShort>16</prodBitPerShort>
        <prodBitPerSizeT>64</prodBitPerSizeT>
        <prodEndianess>1</prodEndianess>
        <prodShiftRight>true</prodShiftRight>
        <prodWordSize>64</prodWordSize>
      </hardwareSettings>
    </configSettingsForConsistencyChecks>
    <controllableInputRatesMap type="ModelRefInfoRepo.VarTsUIDMap" uuid="2c19289b-0b6e-4a83-8d7e-b2ea9157c0c8"/>
    <controllableOutputRatesMap type="ModelRefInfoRepo.VarTsUIDMap" uuid="7b18a223-f5d1-4e60-8795-b7a2c8309142"/>
    <dataPortGroup type="ModelRefInfoRepo.DataPortGroup" uuid="45dfe7e2-984e-4ca9-a45b-0ca6d9f727d9">
      <dataInputPorts>0</dataInputPorts>
      <dataInputPorts>1</dataInputPorts>
      <dataInputPorts>2</dataInputPorts>
      <dataInputPorts>3</dataInputPorts>
      <dataInputPorts>4</dataInputPorts>
      <dataInputPorts>5</dataInputPorts>
      <dataInputPorts>6</dataInputPorts>
      <dataOutputPorts>0</dataOutputPorts>
      <dataOutputPorts>1</dataOutputPorts>
    </dataPortGroup>
    <interfaceParameterInfo type="ModelRefInfoRepo.InterfaceParameterInfo" uuid="15293bd4-cfd6-40a2-86b6-e99965cba27c"/>
    <messageInfo type="ModelRefInfoRepo.MessageInformation" uuid="cf8b55f0-c805-42d0-852d-5d46ec346cd7"/>
    <methodInfo type="ModelRefInfoRepo.MethodExistenceInfo" uuid="e1d332c1-c0da-4ff5-a538-09832abd5b89">
      <hasSystemInitializeMethod>true</hasSystemInitializeMethod>
      <hasTerminateMethod>true</hasTerminateMethod>
    </methodInfo>
    <periodicEventPortUnsupportedBlockInfo type="ModelRefInfoRepo.PeriodicEventPortUnsupportedBlockInfo" uuid="afa6de4d-5898-46f9-970e-eb3b2aeb2cc3"/>
    <portGroupsRequireSameRate type="ModelRefInfoRepo.PortGroupsRequireSameRate" uuid="6b5669e6-3327-4cd6-8443-cab389a399e9">
      <DSMPortGroups type="ModelRefInfoRepo.NameToPortGroupIdxVectMap" uuid="b582f428-34fa-4146-b92b-563199d59759"/>
      <GlobalDSMPortGroups type="ModelRefInfoRepo.NameToPortGroupIdxVectMap" uuid="d7ac3930-522a-4ba3-80f4-d2d6d8a44a62"/>
      <mergedPortGroups type="ModelRefInfoRepo.NameToPortGroupIdxVectMap" uuid="22f9a292-2406-43cd-8397-04d330dc0a0a"/>
    </portGroupsRequireSameRate>
    <rateSpecOfGlobalDSMAccessedByDescExpFcnMdlMap type="ModelRefInfoRepo.GlobalDSMRateSpecMap" uuid="bc30c65b-faf0-403a-a74b-e16622e63e87"/>
    <simulinkFunctions type="ModelRefInfoRepo.SimulinkFunctions" uuid="f7d16e8f-ea35-4b2e-98a4-e2dfb42df292">
      <compSimulinkFunctionCatalog></compSimulinkFunctionCatalog>
      <variantSimulinkFunctions type="ModelRefInfoRepo.VariantSimulinkFunctions" uuid="63dbf377-a97a-4083-9f62-a49ca5baeba9"/>
    </simulinkFunctions>
    <stateWriterToOwnerMap type="ModelRefInfoRepo.StateWriterInfo" uuid="7b2e3ef3-d3f6-40fe-9be7-6fed492797e9"/>
    <stoClientDataRegistry type="sto.ClientDataRegistry" uuid="6f085b64-e067-43f6-87f4-e4bda46c10d8">
      <dataSets type="sto.ClientClockNamedDataSet" uuid="7dcb4409-c8c2-4e48-8fd8-2c4a416bfc37">
        <tag>sltpEvents</tag>
      </dataSets>
      <dataSets type="sto.ClientTaskHierarchyElementNamedDataSet" uuid="3f9d7cb9-ba1e-4242-bdc4-55dd9bdd7686">
        <tag>sltpTaskGroups</tag>
      </dataSets>
      <dataSets type="sto.ClientTaskHierarchyElementNamedDataSet" uuid="bdd52909-96b7-499c-a11d-9833045dc249">
        <dSet type="ModelRefInfoRepo.SltpTaskData" uuid="e61a1d46-411f-4681-a8e2-ba79bf78ca39"/>
        <tSet type="ModelRefInfoRepo.SltpTaskData" uuid="e61a1d46-411f-4681-a8e2-ba79bf78ca39">
          <dataName>D1</dataName>
          <linkedSet type="sto.ClientTaskHierarchyElementNamedDataSet" uuid="bdd52909-96b7-499c-a11d-9833045dc249"/>
          <id type="sto.TaskHierarchyElementId">
            <id>_task0</id>
          </id>
        </tSet>
        <tag>sltpTasks</tag>
      </dataSets>
    </stoClientDataRegistry>
    <varTsUIDMap type="ModelRefInfoRepo.VarTsUIDMap" uuid="b729d38d-ce15-4d59-99a8-2b4cdb15de2b"/>
  </ModelRefInfoRepo.ModelRefInfoRoot>
</MF0>